LICENSE
README.md
gdx_pytest/__init__.py
gdx_pytest/fixtures.py
graphene_django_extensions/__init__.py
graphene_django_extensions/bases.py
graphene_django_extensions/connections.py
graphene_django_extensions/constants.py
graphene_django_extensions/converters.py
graphene_django_extensions/errors.py
graphene_django_extensions/fields/__init__.py
graphene_django_extensions/fields/form.py
graphene_django_extensions/fields/graphql.py
graphene_django_extensions/fields/model.py
graphene_django_extensions/fields/serializer.py
graphene_django_extensions/files.py
graphene_django_extensions/filters.py
graphene_django_extensions/model_operations.py
graphene_django_extensions/options.py
graphene_django_extensions/permissions.py
graphene_django_extensions/py.typed
graphene_django_extensions/serializers.py
graphene_django_extensions/settings.py
graphene_django_extensions/testing/__init__.py
graphene_django_extensions/testing/builders.py
graphene_django_extensions/testing/client.py
graphene_django_extensions/testing/utils.py
graphene_django_extensions/translation.py
graphene_django_extensions/typing.py
graphene_django_extensions/utils.py
graphene_django_extensions/views.py
graphene_django_extensions-0.4.9.dist-info/LICENSE
graphene_django_extensions-0.4.9.dist-info/METADATA
graphene_django_extensions-0.4.9.dist-info/WHEEL
graphene_django_extensions-0.4.9.dist-info/entry_points.txt
graphene_django_extensions-0.4.9.dist-info/RECORD
