Metadata-Version: 2.1
Name: graphene-django-extensions
Version: 0.4.9
Summary: Extensions for graphene-django
Home-page: https://mrthearman.github.io/graphene-django-extensions
License: MIT
Keywords: django,graphene,extensions,graphql,graphene-django,mutations,queries,object_types,fields
Author: Matti Lamppu
Author-email: lamppu.matti.akseli@gmail.com
Requires-Python: >=3.10,<4
Classifier: Environment :: Web Environment
Classifier: Framework :: Django :: 4.2
Classifier: Framework :: Django :: 5.0
Classifier: Framework :: Django :: 5.1
Classifier: Framework :: Pytest
Classifier: Intended Audience :: Developers
Classifier: License :: OSI Approved :: MIT License
Classifier: Natural Language :: English
Classifier: Operating System :: OS Independent
Classifier: Programming Language :: Python
Classifier: Programming Language :: Python :: 3
Classifier: Programming Language :: Python :: 3.10
Classifier: Programming Language :: Python :: 3.11
Classifier: Programming Language :: Python :: 3.12
Classifier: Programming Language :: Python :: 3 :: Only
Classifier: Programming Language :: Python :: 3.13
Provides-Extra: files
Provides-Extra: translation
Requires-Dist: Django (>=4.2)
Requires-Dist: django-filter (>=23.5)
Requires-Dist: django-modeltranslation (>=0.18.13) ; extra == "translation"
Requires-Dist: django-settings-holder (>=0.1.2)
Requires-Dist: djangorestframework (>=3.14.0)
Requires-Dist: graphene-django (>=3.0.0)
Requires-Dist: graphene-django-query-optimizer (>=0.10.3)
Requires-Dist: pillow (>=10.2.0) ; extra == "files"
Requires-Dist: typing-extensions (>=4.12.1) ; python_version < "3.11"
Project-URL: Bug Tracker, https://github.com/MrThearMan/graphene-django-extensions/issues
Project-URL: Documentation, https://mrthearman.github.io/graphene-django-extensions
Project-URL: Repository, https://github.com/MrThearMan/graphene-django-extensions
